<?xml version="1.0" encoding="UTF-8" standalone="no"?>
<pk><wd nm="막으로" rd="47,0:2134|73,0:162|599,0:284"/><wd nm="막은" rd="125,0:58|127,0:70|128,0:68"/><wd nm="막을" rd="462,0:556|635,0:99"/><wd nm="막지" rd="603,0:164|609,0:1444"/><wd nm="만" rd="2,0:79,647,916,1249,1281|4,0:220|7,0:496,1674,1694,1714,3854,4461,4633|11,0:2766,5840|13,0:296|14,0:420|18,0:255|19,0:710|20,0:329,412|21,0:236|22,0:381,826|23,0:671,1504|26,0:164,1341,1701,1969,1979,2047|27,0:846|30,0:65,668|31,0:989|32,0:1518,2053,3266,3347|34,0:1181,1216,1408,1671,1845,2233,2280,2318,2367|35,0:265|36,0:1278,1503,2111,2188,2277|37,0:140|38,0:182,1999|39,0:539|40,0:362|43,0:17,123,258|45,0:1078|46,0:356|47,0:1231,1261|48,0:26|49,0:102|50,0:327,371|53,0:174,267|54,0:642|56,0:127|58,0:127,539|60,0:21,176|61,0:395,2037,2446,2474|63,0:114|64,0:83,948,1456|85,0:276|129,0:110|145,0:182|172,0:139,468|180,0:184|189,0:431|197,0:109|205,0:392|215,0:78|216,0:78,168|217,0:168,279|220,0:159|221,0:115|223,0:106|234,0:2638|236,0:148,5275|240,0:431,478|241,0:1850|246,0:450|249,0:102,1139|250,32:322,335,444|251,0:466,1385,1404|260,0:404,1355,2170|261,0:819,1078,1956|263,0:205|270,0:95,260,1152|271,0:266|272,0:252,332,381,440,473|274,0:131|275,0:224|276,0:133|277,0:185,234,500,695,731,756|278,0:269|279,0:156,501|283,0:167,354|284,0:143|285,0:149|287,0:422,466|288,0:142|289,0:367|291,0:601|295,0:71,135|296,0:65|297,0:939,968,975,994,1007,1018|298,0:173,280|300,0:240,329,463|305,0:424|306,0:1148,1184,1258,1304,1354|307,0:875|308,0:405,520,597,831|309,0:339|311,0:127,169,265|312,0:111,279,619|315,0:132,1247,1495,1534,2248,3320|317,0:848|318,0:695|319,0:432,755|320,0:2030,2492|321,0:1369,1484,1605,1686,1798|324,0:842,1514|327,0:499|328,0:255,263,354,361,706,713|330,0:759,1038|331,0:382,390,406|332,0:587|363,0:437|369,0:713|370,0:64,172|409,0:42|419,0:465,522|420,0:313|424,0:572,1153|431,0:673,1350|433,0:261|435,0:248|441,0:272|442,0:345|443,0:306,399,436|445,0:861|448,0:151,1326|449,0:992|450,0:453|451,0:1189,3221|454,0:684|457,0:639|462,0:180|463,0:220|464,0:2372|466,0:606,1182|467,0:793|468,0:893,1034|474,0:197,713|475,0:320|481,0:112|482,0:460,641,832,1027,1031,1058|484,0:224,244,315,433,874|492,0:337,428|495,0:183,580|498,0:312|499,0:333|510,0:359|512,0:178,254,328|513,0:1099|525,0:80|532,0:605|534,0:1344,1417|542,0:287|543,0:282|551,0:921|552,0:38|554,0:85|555,0:306,481|557,0:375|558,0:1110|559,0:772,833|560,0:77|562,0:133,358,902|564,0:601|568,0:275,323,934|569,0:323,420,3517,4347|571,0:121,126|575,0:67|577,0:555|578,0:46,986,1003,1260,1416|579,0:1180,1218|580,0:330,423,2709|585,0:183|586,0:360|588,0:299,403|589,0:68|590,0:636,716,800|597,0:93,221,722,977,1120,1283,2405,2720|598,0:883|599,0:23|603,0:1360,1885,2375,2515|604,0:662,1495|605,0:118|606,0:549,1501,2321|607,0:182,756,3431|609,0:1294|611,0:157|612,0:243,1157,1220|613,0:2518|614,0:217,292,407|616,0:1171|622,0:82,651|623,0:76,385,1672|624,0:250,351,747|627,0:202,459,503|628,0:179,442,593|630,0:203|632,0:99|634,0:173|637,0:179|641,0:182,190,221|642,0:546|643,0:227,325|644,0:116,315"/><wd nm="만 가능하다" rd="367,0:613"/><wd nm="만 실행된다" rd="633,0:102"/><wd nm="만 유효하다" rd="269,0:900"/><wd nm="만날" rd="472,0:400|523,0:155|528,0:157"/><wd nm="만날때까지" rd="523,0:39|528,0:39"/><wd nm="만드는" rd="561,0:848|620,0:516"/><wd nm="만드는데" rd="559,0:631,660|560,0:1016"/><wd nm="만든" rd="245,0:93|366,0:36|623,0:127"/><wd nm="만든다" rd="114,0:62|146,0:52|149,0:50|559,0:37|560,0:170,1130|561,0:839|563,0:509|564,0:390,420,450,493,896|568,0:842,879|578,0:306|611,0:112"/><wd nm="만들" rd="53,0:196|129,0:300,401|465,0:404|619,0:1111|622,0:327|630,0:42"/><wd nm="만들거나" rd="234,0:2620"/><wd nm="만들고" rd="243,0:227|464,0:2589|578,0:858|618,0:1208|622,0:490"/><wd nm="만들기" rd="119,0:117|129,0:207|242,0:273|307,0:1446"/><wd nm="만들어" rd="37,0:920|38,0:302|450,0:322|474,0:113|559,0:2815|564,0:103|630,0:344,471"/><wd nm="만들어내는" rd="620,0:43"/><wd nm="만들어야" rd="564,0:823"/><wd nm="만들어지고" rd="562,0:506"/><wd nm="만들어지기" rd="14,0:67"/><wd nm="만들어지는" rd="561,0:1102|578,0:1503"/><wd nm="만들어지면" rd="618,0:1006"/><wd nm="만들어진" rd="11,0:62|46,0:245|146,0:55,118|246,0:731,792|560,0:231|569,0:2858|602,0:205|622,0:940|623,0:269"/><wd nm="만들어진다" rd="260,0:2080|561,0:975"/><wd nm="만들어질" rd="630,0:218"/><wd nm="만들지" rd="564,0:672|569,0:2880"/><wd nm="만들지면" rd="630,0:481"/><wd nm="만료된" rd="616,0:316"/><wd nm="만료에" rd="616,0:342"/><wd nm="만약" rd="2,0:1009|4,0:1142|7,0:4422,4855|11,0:1849,2059,2936,3472|12,0:951|14,0:684,901|22,0:1327,1867|31,0:911|32,0:2334|34,0:898,2095,2755,2815,3052,3256|37,0:450|41,0:838|46,0:327|51,0:920|52,0:908|60,0:85|65,0:429|73,0:381|176,0:63|177,0:53|189,0:240|198,0:94|200,0:89|207,0:285|213,0:201,249|219,0:317,354,396|223,0:64|234,0:1470,1864|236,0:3865|241,0:401|242,0:782|257,0:727|260,0:1966,2337|306,0:1090|309,0:108|367,0:583|410,0:56|411,0:68|413,0:642|416,0:223|417,0:118|420,0:117|422,0:147|426,0:107|427,0:165|430,0:71,93|432,0:86,107|433,0:134,163|435,0:110,144|441,0:208,253|445,0:498,1185|447,0:310|454,0:294,591|456,0:483,571|465,0:84|473,0:87,144|559,0:2374|560,0:209|563,0:416,1186,1306,1413|564,0:50,609|568,0:601|569,0:429,1211,2869,4688|571,0:129|577,0:622,772|580,0:133,3296|586,0:211|597,0:164,2969|598,0:1124,1206,1304,1410,1491,1592,1680,1843,1943,2044|599,0:267|610,0:222|614,0:660,759,892|616,0:175,300,527,596,659,759|619,0:1089|632,0:110|642,0:61"/><wd nm="만약 score" rd="628,0:412"/><wd nm="만약 지정한" rd="7,0:4593"/><wd nm="만약 테이블" rd="441,0:475|642,0:555|643,0:255"/><wd nm="만약에" rd="236,0:2347"/><wd nm="만으로" rd="38,0:278|644,0:272"/><wd nm="만으로는" rd="579,0:1639"/><wd nm="만으로의" rd="261,0:594"/><wd nm="만을" rd="2,0:566|26,0:1142|36,0:32,89|80,0:50|114,0:84|189,0:178,389|237,0:1310,1390|246,0:62|460,0:387|467,0:675,1171,1219|474,0:214,750|480,0:404|497,0:232,321|520,0:61|563,0:455,1066|568,0:873|590,0:783"/><wd nm="만을 부여하기" rd="367,0:555"/><wd nm="만의" rd="424,0:1117|425,0:545|426,0:531"/><wd nm="만이" rd="11,0:121|24,0:218|36,0:1899|51,0:1329|233,0:391|259,0:729|451,0:3281|456,0:991|569,0:5011|596,0:258|632,0:173"/><wd nm="만인" rd="569,0:889,2379"/><wd nm="만일" rd="10,0:123|590,0:663"/><wd nm="만족되는" rd="468,0:587"/><wd nm="만족되지" rd="468,0:719"/><wd nm="만족된다" rd="468,0:664,706"/><wd nm="만족시킬" rd="35,0:186"/><wd nm="만족하기" rd="37,0:52"/><wd nm="만족하는" rd="43,0:300|439,0:81|443,0:395|559,0:64,201|562,0:129,354,786|598,0:2010|605,0:314|608,0:208|609,0:948|613,0:2441,2482"/><wd nm="만족하는 데이터만" rd="442,0:345"/><wd nm="만족하는 모든" rd="439,0:107"/><wd nm="만족하지" rd="324,0:1065|613,0:2538"/><wd nm="만족한다면" rd="644,0:71"/><wd nm="만족할" rd="620,0:407"/><wd nm="만족해야" rd="52,0:103"/><wd nm="만큼" rd="2,0:1693,1736|7,0:3031|8,0:263|28,0:555|164,0:79|213,0:106|272,0:795|277,0:626|306,0:701|308,0:235|530,0:577|580,0:1994"/><wd nm="만큼 큰" rd="297,0:256"/><wd nm="만큼만" rd="433,0:261|435,0:248"/><wd nm="만큼을" rd="518,0:262|530,0:65"/><wd nm="만큼의" rd="259,0:244|269,0:781|324,0:364,551|464,0:2964|485,0:186|616,0:740"/><wd nm="만큼이나" rd="623,0:131"/><wd nm="만한" rd="37,0:893"/><wd nm="많거나" rd="308,0:674"/><wd nm="많고" rd="322,0:461"/><wd nm="많다" rd="614,0:318"/><wd nm="많더라도" rd="628,0:163,569"/><wd nm="많아지므로" rd="323,0:386"/><wd nm="많은" rd="23,0:1656|31,0:999|32,0:3512|37,0:184,221|235,0:594|315,0:1882|322,0:471|472,0:329|561,0:1547|601,0:163|610,0:433|614,0:299|620,0:180|622,0:512|634,0:84"/><wd nm="많이" rd="306,0:574|320,0:2674|322,0:313"/><wd nm="말" rd="45,0:243|51,0:283|247,0:200|248,0:885,918,1734|264,32:290,295,321|303,32:86,93,146"/><wd nm="말로" rd="252,0:1518"/><wd nm="말을" rd="253,0:1081|303,0:100,115"/><wd nm="말이" rd="264,0:486"/><wd nm="말지" rd="431,0:1187"/><wd nm="말하기도" rd="598,0:1378"/><wd nm="말하면" rd="590,0:660"/><wd nm="말하자면" rd="637,0:95"/><wd nm="말한다" rd="315,0:1435|580,0:658,1186|628,0:66"/><wd nm="말해서" rd="586,0:24"/><wd nm="맞게" rd="185,0:185|186,0:31|191,0:490|297,0:821|451,0:1259|459,0:36|569,0:6130"/><wd nm="맞는" rd="306,0:963|534,0:140,1816|535,0:39|536,0:51|537,0:42|538,0:42|539,0:54|598,0:1825"/><wd nm="맞아야" rd="206,0:289"/><wd nm="맞은" rd="243,0:3347|551,0:674"/><wd nm="맞지" rd="289,0:215,240"/><wd nm="맞추어" rd="448,0:154|563,0:691"/><wd nm="맞춰" rd="249,0:2530|250,0:465"/><wd nm="맞춰서" rd="0,0:110"/><wd nm="매개" rd="268,0:409|269,0:16|271,0:157|287,0:24,71,137,233,253,273,296|297,0:95,108,142,188,417,490,614,637,722,749,834|301,0:167|302,0:153,376|303,0:313|618,0:503,515"/><wd nm="매개변수" rd="386,0:182,227|387,0:133,157,179|405,0:189|406,0:137,161,185"/><wd nm="매개변수나" rd="616,0:95"/><wd nm="매개변수를" rd="172,0:373"/><wd nm="매개변수와" rd="451,0:1244|609,0:32"/><wd nm="매개변수의" rd="616,0:919"/><wd nm="매뉴얼" rd="237,128:0,5,10,745,1680"/><wd nm="매뉴얼에서" rd="237,0:773"/><wd nm="매뉴얼에서는" rd="365,0:56"/><wd nm="매뉴얼을" rd="264,0:313"/><wd nm="매뉴얼의" rd="237,0:60"/><wd nm="매니저" rd="0,0:172|62,32:695,734,753,801|63,0:40|66,128:6,19,32,71,202,234,364|67,128:6,17,31,42,91,201,212,411|71,0:240,247|237,0:355,437,573,622,641|238,0:181|248,0:142|249,0:1220|250,0:143|251,0:25|252,16:11,42,386,421,512,587,618,1118,1196,1218,1273,1303,1469,1538|256,0:425|262,128:6,15,183,213,284,295,306,422|263,0:42,101,261|264,0:100,133|265,128:6,17,69,86,98,117,157,173,196,312,372,416,536|270,0:87|271,0:37|277,0:50|278,0:51|279,0:332,347,389|290,0:157|295,128:6,22,61,80,101,341,398,414,494,521,542,662|296,128:6,19,55,74,301,355,368,622,753|297,4:12,27,165,464,514,532|298,0:296|300,0:76,102,127,167|301,0:12|302,0:133,303,805,1356|303,0:33,195|304,0:20|305,0:679|306,0:1140,1228|307,0:1787|310,0:83,95|311,0:50,90,153|312,0:248,312,475|313,0:87,160|320,0:526|329,0:175|330,0:37,43,240,394,404,479,492,545,603|331,128:0,34,55,263,447,465,1181|413,0:745"/><wd nm="매니저가" rd="252,0:1031,1084|297,0:582"/></pk>