<?xml version="1.0" encoding="UTF-8" standalone="no"?>
<pk><wd nm="변경하거나" rd="3,0:329|366,0:455|541,0:410"/><wd nm="변경하고" rd="50,0:47|269,0:568|274,0:320|284,0:360|616,0:1294"/><wd nm="변경하고자" rd="51,0:1595,1640|58,0:397|227,0:242|284,0:227|550,0:126"/><wd nm="변경하고자 하는 파라미터 번호" rd="45,0:1980"/><wd nm="변경하기" rd="22,0:357|58,0:303|227,0:214|316,0:911|329,0:2426|331,0:518|575,0:103|594,0:478|642,0:620"/><wd nm="변경하는" rd="0,0:113|253,0:1066|443,0:472|547,0:650|550,0:170|557,0:292|570,0:957|590,0:966|594,0:568|595,0:357|596,0:191|597,0:50,228|624,0:422|642,0:336|648,0:274|650,0:200"/><wd nm="변경하려는" rd="438,0:327"/><wd nm="변경하려는 테이블의" rd="547,0:431"/><wd nm="변경하려면" rd="249,0:2535|250,0:470|284,0:30|547,0:42|550,0:49|642,0:565|643,0:268"/><wd nm="변경하면" rd="11,0:2998|26,0:1595,1751|547,0:101|555,0:550|575,0:15|576,0:22"/><wd nm="변경하면서" rd="22,0:1018,1782"/><wd nm="변경하므로" rd="36,0:1261"/><wd nm="변경하여" rd="12,0:709|45,0:1576|51,0:1250|306,0:1109,1268|312,0:445|392,0:60|578,0:570"/><wd nm="변경하여야" rd="455,0:209"/><wd nm="변경하지" rd="45,0:2054|51,0:612"/><wd nm="변경하지는" rd="630,0:168"/><wd nm="변경한" rd="3,0:350|7,0:6015|22,0:725|25,0:583|44,0:192|50,0:159|252,0:789|369,0:263"/><wd nm="변경한다" rd="22,0:51,82,129,154|52,0:835,1244,1303|59,0:2882|160,0:104|166,0:55|227,0:73|236,0:3069,6236|250,0:504|570,0:414|595,0:434|619,0:430|624,0:626|642,0:264,284|643,0:47"/><wd nm="변경할" rd="12,0:720|26,0:2043|30,0:302|45,0:2379|51,0:43|58,0:149,160,379|236,0:5281,5295|253,0:89,1043|270,0:397|289,0:1319|293,0:467|294,0:405|302,0:413|306,0:1027,1152|312,0:624,652|328,0:109,509|369,0:197,222|448,0:1922|534,0:543|558,0:1014,1034|565,0:478|578,0:215|579,0:1058|580,0:166|582,0:285|591,0:537|592,0:352|594,0:51,386,426,511|595,0:70,214,254,314|596,0:36,117|597,0:1425,1708,2088,2108|623,0:756|631,0:666,821|642,0:55,208|643,0:145,332|648,0:61,137,161|650,0:43,121"/><wd nm="변경할 수" rd="596,0:287"/><wd nm="변경함으로써" rd="597,0:1813"/><wd nm="변경해서" rd="241,0:1854"/><wd nm="변경해서는" rd="260,0:957"/><wd nm="변경해야" rd="53,0:1106|189,0:234|252,0:783|316,0:872|317,0:350|329,0:2386|331,0:478"/><wd nm="변경했다면" rd="628,0:395"/><wd nm="변길이" rd="411,0:24|412,0:104,519|431,0:65,99,640,1295|434,0:21|435,0:46"/><wd nm="변길이든" rd="431,0:493"/><wd nm="변길이의" rd="433,0:28"/><wd nm="변성" rd="590,128:3,9,56,61,66,73,96,234,403,948,1112"/><wd nm="변성과" rd="590,0:982"/><wd nm="변성에서" rd="597,0:17"/><wd nm="변성은" rd="590,0:21,345,442,531|597,0:883"/><wd nm="변성을" rd="590,0:888|597,0:73,384,452"/><wd nm="변성의" rd="597,0:425,2428"/><wd nm="변성이" rd="590,0:83"/><wd nm="변수" rd="8,0:1920|12,0:687|47,0:2079|237,0:842|242,0:264,269,280,313,318,331,504|253,128:2,8,104,591,916,1010,1022,1232,1750|268,0:323|269,0:26|287,32:118,179,193,336,382,390,399|297,0:97,110,751|302,0:136,306,808|303,32:385,428|315,0:3279|316,32:1517|336,128:5,12,694|386,0:182,227|387,0:133,157,179|405,0:189|406,0:137,161,185|432,0:287|446,0:275|456,0:422,949|464,0:761|568,0:483"/><wd nm="변수가" rd="12,0:1074|59,0:2215|242,0:102|248,0:327|253,0:898|254,0:316|301,0:169|302,0:155|315,0:3396"/><wd nm="변수나" rd="616,0:95"/><wd nm="변수는" rd="242,0:241,293|253,0:452|297,0:144|302,0:378"/><wd nm="변수들은" rd="253,0:50"/><wd nm="변수들이" rd="253,0:32"/><wd nm="변수로" rd="12,0:206|242,0:197|254,0:45|297,0:190,419,492,616,724|618,0:505"/><wd nm="변수를" rd="47,0:1511|172,0:373|242,0:635|253,0:163,420,971,1063|271,0:159|287,0:26,73,139,235,255,275|303,0:315,395|315,0:3166,3227|316,0:1544|446,0:125,232|454,0:609,663|464,0:472|534,0:724|535,0:458|536,0:489|538,0:461|539,0:500"/><wd nm="변수명에" rd="364,0:44"/><wd nm="변수에" rd="7,0:2764,2903|191,0:61|242,0:210|253,0:719|254,0:67|268,0:411|287,0:298|297,0:639|454,0:336|464,0:720,1019,1031,3619,4565|467,32:1136,1152,1188|568,0:707,764|616,0:734,932|618,0:517"/><wd nm="변수에는" rd="253,0:612,789"/><wd nm="변수에서" rd="12,0:971|454,0:277,570|496,0:930"/><wd nm="변수와" rd="451,0:1244|609,0:32"/><wd nm="변수의" rd="254,0:335|456,0:654,1013|464,0:773|616,0:919"/><wd nm="변수이다" rd="253,0:136,221,349|297,0:836"/><wd nm="변수인" rd="464,0:671"/><wd nm="변영된" rd="49,0:817"/><wd nm="변이든" rd="432,0:479|433,0:481"/><wd nm="변하는" rd="468,0:34"/><wd nm="변하지" rd="324,0:583|464,0:3064|467,0:420"/><wd nm="변할" rd="464,0:3582"/><wd nm="변화" rd="26,0:2100,2177"/><wd nm="변화는" rd="620,0:269"/><wd nm="변화된" rd="577,0:39"/><wd nm="변화를" rd="618,0:618"/><wd nm="변환" rd="412,0:495|413,0:806|419,0:432,572,635|424,32:892|425,0:426|426,0:417|431,32:1265|448,0:1268|467,32:1014,1039|496,32:345"/><wd nm="변환되거나" rd="254,0:231"/><wd nm="변환되고" rd="467,0:958|496,0:559,614,688,870"/><wd nm="변환되며" rd="496,0:441"/><wd nm="변환되어" rd="127,0:132|191,0:492|431,0:1420|586,0:1514"/><wd nm="변환되어야" rd="496,0:370"/><wd nm="변환된" rd="425,0:421|426,0:412|467,0:619"/><wd nm="변환된다" rd="424,0:1018|467,0:1119|474,0:448|485,0:375|496,0:738,820"/><wd nm="변환될" rd="413,0:835|419,0:565,628,682,719|466,0:1124|513,0:121|590,0:934"/><wd nm="변환만" rd="419,0:522"/><wd nm="변환시키고" rd="153,0:49|154,0:45"/><wd nm="변환시킨다" rd="53,0:1187"/><wd nm="변환에" rd="466,0:126|569,0:1711|614,0:1054"/><wd nm="변환은" rd="412,0:553|413,0:845|419,0:498,732|424,0:962|431,0:1333|466,0:1164|467,0:1057|496,0:488"/><wd nm="변환이" rd="412,0:541|424,0:950|431,0:1326|496,0:403|564,0:724"/><wd nm="변환하는" rd="535,0:512,599|536,0:535,719|538,0:597|539,0:661"/><wd nm="변환하는데" rd="466,0:57"/><wd nm="변환하여" rd="73,0:88|175,0:211|180,0:65|466,0:1037|533,0:187|537,0:453,546|538,0:512|539,0:548"/><wd nm="변환하지" rd="513,0:1201"/><wd nm="변환한" rd="424,0:1090|513,0:711|521,0:54|533,0:54"/><wd nm="변환한다" rd="513,0:659|534,0:153,1831|535,0:53|536,0:69|537,0:59|538,0:52|539,0:73"/><wd nm="변환할" rd="179,0:91|420,0:168|425,0:412|426,0:403|431,0:1439|466,0:95,586,968,988,1225|521,0:137|533,0:137|534,0:2014|535,0:287|536,0:311|537,0:322|538,0:286|539,0:317|559,0:1902"/><wd nm="변환해" rd="485,0:294"/><wd nm="변환해주어야" rd="486,0:320|487,0:167|513,0:144"/><wd nm="변환했을" rd="420,0:294"/><wd nm="별" rd="2,0:43|12,0:284|47,0:1176|53,0:298|58,0:86|237,0:453|250,0:785|251,0:269|259,0:182|267,128:0,7,21,34,237|269,0:430|270,0:754|271,32:52,168,183|274,0:281|284,0:319|304,0:255|307,0:1206|308,0:52|313,0:106|315,128:0,8,3938|316,0:121|321,0:1891|329,32:2115|332,0:594|561,0:73,891|568,0:530|569,0:898,3559|644,0:718|647,0:290"/><wd nm="별개로" rd="40,0:211"/><wd nm="별구분" rd="569,0:2388"/><wd nm="별도로" rd="2,0:1210|36,0:1053,1474|63,0:92|250,0:218|260,0:287|307,0:1762|482,0:677"/><wd nm="별도의" rd="29,0:135|32,0:567|36,0:844|37,0:749|38,0:396,1273|40,0:113|49,0:722|59,0:2754|233,0:330|235,0:842|239,0:189|302,0:1283,1322|307,0:1371,1799|396,0:1247|449,0:320|585,0:340|644,0:437"/><wd nm="별되어야" rd="562,0:257"/><wd nm="별된" rd="580,0:1969"/><wd nm="별된다" rd="441,0:425|580,0:770|625,0:64"/><wd nm="별로" rd="6,0:321|8,0:439|38,0:1765|48,0:424|49,0:912|53,0:671,756,1250|239,0:637|251,0:1343,1497|259,0:24,192,316,361|264,0:54|270,0:726,1105|289,0:932,1088|293,0:373,399|302,0:1279|303,0:64|305,0:382|307,0:1045,1367|308,0:773|562,0:441,712|567,0:106"/><wd nm="별명" rd="307,0:1265"/><wd nm="별명으로" rd="578,0:638"/><wd nm="별을" rd="31,0:234"/><wd nm="별이" rd="468,0:1306"/><wd nm="별자" rd="8,0:1058|11,0:4424|31,32:252,283,1866|41,0:219,469,1106,1492,1523|336,4:0,7|363,128:0,3,6,403,413,515,537,635,647,698,830|376,0:111|389,0:61|392,0:42|464,0:1039|474,0:785"/><wd nm="별자," rd="336,128:687"/><wd nm="별자는" rd="260,0:1804|363,0:29,668"/><wd nm="별자도" rd="363,0:708"/><wd nm="별자를" rd="31,0:307,439,1899|260,0:657|292,0:252|363,0:561|568,0:737"/><wd nm="별자의" rd="206,0:282|363,0:416,460,585"/><wd nm="별자이다" rd="260,0:1797"/><wd nm="별적" rd="22,0:1092"/><wd nm="별적으로" rd="315,0:23,3154|329,0:2211,2245|366,0:111|614,0:426"/><wd nm="별적인" rd="467,0:413|628,0:267"/><wd nm="별칭" rd="31,0:243|567,0:238|588,0:434"/><wd nm="별칭을" rd="583,0:451"/><wd nm="별표" rd="568,0:1132"/><wd nm="별하게" rd="413,0:442"/><wd nm="별하고" rd="569,0:1998"/><wd nm="별하기" rd="22,0:1200|36,0:1807|193,0:259|207,0:354|636,0:238"/><wd nm="별하는" rd="580,0:698"/><wd nm="별하는데" rd="237,0:802"/><wd nm="별하지" rd="51,0:1031,1184|363,0:76|451,0:261"/><wd nm="별한" rd="236,0:42|270,0:428|424,0:784|462,0:249"/><wd nm="별할" rd="580,0:643"/><wd nm="별할지" rd="297,0:714"/><wd nm="별해서" rd="11,0:737|32,0:681,1138|34,0:1026"/><wd nm="별히" rd="246,0:54"/><wd nm="병렬" rd="2,32:149,1652,1658,1749|7,0:469,1004,2944,2995,3045|272,0:752|277,0:585|599,0:163"/><wd nm="병합" rd="260,0:1674|467,0:380|494,0:30,61,77|517,128:0,5,12,61,507|564,0:441"/><wd nm="병합을" rd="517,0:91"/><wd nm="병합할" rd="501,0:112|517,0:260"/><wd nm="병행될" rd="22,0:909,1086"/><wd nm="보" rd="4,0:378,451,569,793,909,968,1011|7,0:742,2098,4272,4880,4934,4958,4987,6035,6152,6221,6343|8,0:2117|11,0:3451,3933,3980,4060,4106,4154,4885,5095,5179,5541,5657,5666,5696,5870|12,0:86,105,279,351,640,734,783,1025,1045,1101|13,128:8,20,756|14,0:649,888,922|15,0:866|18,128:2,8,653|19,0:556,734,797|22,0:55,397,1218,1810,1888|29,32:1458,1514|32,0:2106,3740|34,0:2410|41,0:71,75,1402,1769|44,0:315|45,0:1040|47,0:1836|50,0:815,870|52,0:1093|53,0:1095,1262|61,0:538,1541|68,0:504,547,627,708,889|101,0:307|102,0:285|103,0:256|104,0:251|105,0:244|106,0:230|107,0:226|120,0:78,290,511,593,1005|223,0:102|230,0:102|235,0:529|236,0:4091,5523|237,0:544|248,0:1468,1636|251,0:1137,1566|252,32:1489,1722,1734,1743|253,0:207,993|260,0:612,616,631,690,727,740,742,759,793,820,867,919|264,0:605,617|269,0:136,435,655|270,32:154,457,541,634,793,1391|275,32:85,152|277,0:520|279,0:197|280,128:8,18,71,107,128,137,159,191,222,357|285,0:371,556,594|289,16:1376|290,128:10,22,79,117,140,350|292,0:176|293,32:148,357,364|294,32:437|297,0:1063|298,0:142|300,128:5,12,781|302,32:1058|303,32:162,168,244,459,465|305,32:92,153,187,204,223|306,32:178,807,1043|307,0:1741,1777|308,0:99,250,511,588,741|312,0:36|317,0:600|321,0:2243|365,0:328|372,0:686|374,0:57|375,0:102|377,0:475|380,0:100|382,0:369|385,0:101|389,0:214|451,0:1902|553,128:8,20,318|566,128:2,8,446|580,0:720"/></pk>