<?xml version="1.0" encoding="UTF-8" standalone="no"?>
<pk><wd nm="경하기" rd="22,0:357|58,0:303|227,0:214|316,0:911|329,0:2426|331,0:518|575,0:103|594,0:478|642,0:620"/><wd nm="경하는" rd="0,0:113|253,0:1066|443,0:472|547,0:650|550,0:170|557,0:292|570,0:957|590,0:966|594,0:568|595,0:357|596,0:191|597,0:50,228|624,0:422|642,0:336|648,0:274|650,0:200"/><wd nm="경하려는" rd="438,0:327"/><wd nm="경하려는 테이블의" rd="547,0:431"/><wd nm="경하려면" rd="249,0:2535|250,0:470|284,0:30|547,0:42|550,0:49|642,0:565|643,0:268"/><wd nm="경하면" rd="11,0:2998|26,0:1595,1751|547,0:101|555,0:550|575,0:15|576,0:22"/><wd nm="경하면서" rd="22,0:1018,1782"/><wd nm="경하므로" rd="36,0:1261"/><wd nm="경하여" rd="12,0:709|45,0:1576|51,0:1250|306,0:1109,1268|312,0:445|392,0:60|578,0:570"/><wd nm="경하여야" rd="455,0:209"/><wd nm="경하지" rd="45,0:2054|51,0:612"/><wd nm="경하지는" rd="630,0:168"/><wd nm="경한" rd="3,0:350|7,0:6015|22,0:725|25,0:583|44,0:192|50,0:159|252,0:789|369,0:263"/><wd nm="경한다" rd="22,0:51,82,129,154|52,0:835,1244,1303|59,0:2882|160,0:104|166,0:55|227,0:73|236,0:3069,6236|250,0:504|570,0:414|595,0:434|619,0:430|624,0:626|642,0:264,284|643,0:47"/><wd nm="경할" rd="12,0:720|26,0:2043|30,0:302|45,0:2379|51,0:43|58,0:149,160,379|236,0:5281,5295|253,0:89,1043|270,0:397|289,0:1319|293,0:467|294,0:405|302,0:413|306,0:1027,1152|312,0:624,652|328,0:109,509|369,0:197,222|448,0:1922|534,0:543|558,0:1014,1034|565,0:478|578,0:215|579,0:1058|580,0:166|582,0:285|591,0:537|592,0:352|594,0:51,386,426,511|595,0:70,214,254,314|596,0:36,117|597,0:1425,1708,2088,2108|623,0:756|631,0:666,821|642,0:55,208|643,0:145,332|648,0:61,137,161|650,0:43,121"/><wd nm="경할 수" rd="596,0:287"/><wd nm="경함으로써" rd="597,0:1813"/><wd nm="경해서" rd="241,0:1854"/><wd nm="경해서는" rd="260,0:957"/><wd nm="경해야" rd="53,0:1106|189,0:234|252,0:783|316,0:872|317,0:350|329,0:2386|331,0:478"/><wd nm="경했다면" rd="628,0:395"/><wd nm="경험할" rd="609,0:1122"/><wd nm="계" rd="18,128:0,6,60,80,228,304,341,386,441,515,651|27,0:445,496|31,32:799,1384|32,0:2192,3632|34,0:2786,2819|36,0:2275|40,0:34|41,0:1400|44,128:4,10,31,635|45,0:1257,1542,1701,2010,2088,2318|47,0:1086|52,32:366,600,795,1048,1068,1502,1610,1889|68,0:625|172,32:384|235,0:553|236,0:5553|259,0:308|261,0:2621|270,32:135,693,1081,1322,1386|277,0:518,529|278,0:336|327,0:513,533,552|375,0:416,456|397,0:151|420,0:216|431,0:1115|455,128:14,30,931|481,0:131|484,0:452|513,128:0,5,12,78,386,459,499,593,867,1216,1250,1370|553,128:6,18,31,316|562,0:55|566,128:0,6,47,59,335,444|568,0:590,615,658|569,0:787|576,0:255|589,0:91|598,0:411|603,0:548|604,0:654|605,0:344|606,0:540|607,0:748|608,0:238|615,0:15|644,0:234"/><wd nm="계1" rd="45,0:864,1303|46,0:66|47,0:1703|48,0:452"/><wd nm="계2" rd="45,0:1374|46,0:148|47,0:1725|48,0:733"/><wd nm="계3" rd="45,0:1438|46,0:229|47,0:1751"/><wd nm="계4" rd="45,0:1507|47,0:1787"/><wd nm="계5" rd="45,0:1535|47,0:1820"/><wd nm="계6" rd="45,0:2001|47,0:2072"/><wd nm="계7" rd="45,0:2309"/><wd nm="계가" rd="36,0:1120|261,0:2414|431,0:1253|477,0:135|578,0:1500|597,0:131,1182|630,0:182"/><wd nm="계까지" rd="270,0:1395"/><wd nm="계는" rd="45,0:1687|52,0:1512|218,0:33|451,0:1295|618,0:804"/><wd nm="계도" rd="501,0:48"/><wd nm="계되었다" rd="40,0:278|186,0:33"/><wd nm="계로" rd="44,0:20|45,0:853|47,0:60,1075,2093|270,0:71,1439|305,0:693|327,0:337|613,0:2466"/><wd nm="계로는" rd="50,0:30"/><wd nm="계로서" rd="44,0:71"/><wd nm="계를" rd="11,0:5829|26,0:865,1611,1768|27,0:389,511|31,0:1314,1433,1641|32,0:1591|172,0:1200|261,0:2533|327,0:411,453,488|371,0:69|431,0:1131,1212|485,0:212|501,0:24,98,233,273,321|580,0:2651,2870,2908|583,0:70|589,0:41|597,0:112,2296,2796|622,0:487"/><wd nm="계별" rd="47,0:1176"/><wd nm="계별로" rd="239,0:637|303,0:64|307,0:1045"/><wd nm="계산" rd="467,0:944|497,0:279"/><wd nm="계산과" rd="424,0:95"/><wd nm="계산되며" rd="467,0:623"/><wd nm="계산된" rd="485,0:55,201"/><wd nm="계산된다" rd="481,0:203|484,0:785|562,0:539"/><wd nm="계산될" rd="424,0:1001|501,0:51"/><wd nm="계산됨" rd="61,0:2448,2476"/><wd nm="계산하거나" rd="460,0:214"/><wd nm="계산하게" rd="529,0:199"/><wd nm="계산하고" rd="563,0:471"/><wd nm="계산하는" rd="495,0:862|502,0:54|585,0:298"/><wd nm="계산할" rd="467,0:698|496,0:352|497,0:210|501,0:101"/><wd nm="계속" rd="3,0:216|26,0:468,614,925,1066|47,0:2544|234,0:873,2452,2492|306,0:501|464,0:4283|609,0:1814|613,0:3403|622,0:225|636,0:138"/><wd nm="계속하기" rd="7,0:5999"/><wd nm="계속해서" rd="450,0:328"/><wd nm="계없이" rd="330,0:803|372,0:540|393,0:723|498,0:339|499,0:360"/><wd nm="계에" rd="31,0:298|172,0:1184|580,0:1156"/><wd nm="계에서" rd="270,0:816,1064|576,0:257|613,0:2421,2507,2526"/><wd nm="계열에만" rd="261,0:819"/><wd nm="계열에서만" rd="27,0:846|35,0:265|43,0:17"/><wd nm="계와" rd="332,0:353"/><wd nm="계이다" rd="218,0:446"/><wd nm="계이며" rd="371,0:82"/><wd nm="계자에게" rd="597,0:265"/><wd nm="계적으로" rd="635,0:50"/><wd nm="계정" rd="32,0:1661|36,0:856,1182,1738|41,0:1033,1254,1284|47,0:260,1762|52,32:193,395,1054,1122,1894|53,0:1093|55,0:633,650|312,32:34,66,300,342"/><wd nm="계정만" rd="270,0:95"/><wd nm="계정에" rd="312,0:611"/><wd nm="계정으로" rd="36,0:1257,1284|45,0:1572|47,0:206,863|300,0:442"/><wd nm="계정은" rd="36,0:1150,1272|40,0:334,484|293,0:304|312,0:704"/><wd nm="계정을" rd="32,0:1170,1696|36,0:1169,1249|45,0:1295|47,0:877,1284,1780|52,0:230,1182,1222,1235,1900|293,0:490"/><wd nm="계정의" rd="36,0:1133|45,0:136,1207|52,0:1164|253,0:1171|270,0:1350"/><wd nm="계정이" rd="45,0:1277,1653|52,0:1211"/><wd nm="계정인" rd="311,0:107,257"/><wd nm="계층" rd="257,0:108|371,0:178|577,0:761,783,821,1098,1140,1376,1477|578,0:1451|584,0:44|586,0:433|587,0:27,45|590,0:54,94,156,242|597,32:335,442,450,1147,2873,2912"/><wd nm="계층으로" rd="614,0:84"/><wd nm="계층이" rd="464,0:5528"/><wd nm="계층적" rd="36,0:1962"/><wd nm="계층형" rd="307,0:898,1057"/><wd nm="계하는" rd="256,0:270|257,0:37,530|258,0:507"/><wd nm="계하여" rd="580,0:2597"/><wd nm="계한다" rd="257,0:959"/><wd nm="계함수" rd="626,0:485"/><wd nm="계형" rd="185,0:165,177|186,0:23,93,115|255,0:42|256,0:19|261,16:1912,1925,2367|365,0:41,71,156,189|413,0:38|586,0:1562,1616"/><wd nm="계획" rd="21,128:4,14,309,343,389,545|71,0:563|236,0:5371,5397|251,0:698,727|257,0:466|269,0:880|306,0:718|307,128:4,12,29,54,76,199,228,300,424,449,466,484,504,523,556,584,599,607,642,690,728,736,795,817,861,873,884,927,972,980,1031,1038,1488,1502,1524,1531,1569,1621,1646,1663,1671,1711,1941|309,0:571,600|565,128:4,12,34,275,535,576,858,1293"/><wd nm="계획과" rd="307,0:344,1682"/><wd nm="계획도" rd="307,0:148"/><wd nm="계획들의" rd="21,0:58"/><wd nm="계획상의" rd="307,0:1201"/><wd nm="계획에" rd="307,0:434"/><wd nm="계획에서" rd="307,0:1385"/><wd nm="계획은" rd="307,0:417|565,0:191"/><wd nm="계획을" rd="21,0:213,273|236,0:5452,5471,5502|251,0:712|306,0:744|307,0:127,214,239,257,287,401,536,714,750,806,1540,1588,1641|309,0:585|320,0:1081|563,0:506,521|564,0:100,387,417,447,488,669,820,893|565,0:415,499,639,709,758,793"/><wd nm="계획의" rd="307,0:1512|565,0:175"/><wd nm="계획이" rd="277,0:111|307,0:170,512,1052|320,0:1942"/><wd nm="고" rd="0,0:157,188|2,0:353,596,1024,1048,1322,1595|4,0:43,121,574,610,823|6,0:471|7,0:528,1506,3252,3431,3888,4952,5334,6275,7190|8,0:302,355,435,992,1691,1915|10,0:468|11,0:56,537,590,1745,1962,2033,2629,4360|12,0:184,821|14,0:489|17,0:53,197|19,0:283|20,0:73,499|22,0:1115|23,0:194,326,959,1646|24,0:120,204|26,0:291,602,690,992,1657,1813|27,0:706,796|28,0:402|29,0:1579|30,0:757|31,0:1401,1505|32,0:656,1251,1521,1594,1898,1938,2033,2491,3634,3674|33,0:781,985,1064|34,0:584,1176,1211,2840,3233|35,0:247,275|36,0:634,1558,2000|37,0:174,190,206,232,541,576,805,865,869,932|38,0:82,665,1066,1206,1250,1261,1718|39,0:336,540|40,0:234,365|41,0:198,339,448,1085,1462,1775|42,0:51,140,213|44,0:52,404,488|45,0:1070,1230,1596,2266,2480|46,0:164,359|47,0:1253,1855,1885,2546|48,0:690,961,1142|49,0:21,734,830,960,968|50,0:47|51,0:1011,1164,1306|52,0:558,676|53,0:44,247,257|55,0:383,502|58,0:363|59,0:865,2253,3139|61,0:159,385,2646,3215|63,0:230|68,0:1177|73,0:330,370|77,0:54|80,0:54|81,0:94|84,0:95|85,0:254,385|87,0:97|94,0:65,94|100,0:98|119,0:33|127,0:105|135,0:73,1660,1743|145,0:133,189|150,0:55|153,0:49|154,0:45|156,0:28|157,0:35|168,0:57|169,0:69|172,0:173,1087,1120|173,0:57,204,220,551|178,0:69|181,0:53|183,0:53|185,0:155|188,0:42,73|189,0:396,442|192,0:86|193,0:273,279|200,0:67|205,0:87|206,0:395|207,0:84,368,374|213,0:199|214,0:197,231|216,0:113|217,0:135|218,0:197,239,258,408,716,1689,1739|219,0:563,689|220,0:93,157|222,0:182|223,0:266,289,312|225,0:206|229,0:227|233,0:73,145,223|234,0:51,871,965,1017,1271,1737,1927,2104,2204,2448,2488,2632,2768,2939|235,0:91,198,347|236,0:56,139,2322,2391,3495,3551,3701|237,0:787|238,0:104|240,0:423,522|241,0:242|242,0:89,200,723|243,0:163,227,3352,3366|244,0:299,407|245,0:502|246,0:446|247,0:27|248,0:53,179,577,797|249,0:2089,2360,2585,2624|250,0:102|251,0:62,71,218,515,588,685,808,1078,1302,1371,1388,1428|252,0:261,287,452,693,872,1012,1231,1418,1563,1590,1773|253,0:314,448,885,1004,1165|254,0:208|256,0:132,156|257,0:620,701,816|259,0:400,404,652,725,801|260,0:84,496,650,1085,1787,2265|261,0:315,448,782,1389,1430,1696,1874,2302|263,0:70,195,298|264,0:34,331,413,439|265,0:75|267,0:115|268,0:99,187,316,345|269,0:79,239,293,416,447,568,581|270,0:210,860,1290,1374|272,0:90,292|273,0:86|274,0:69,320|275,0:365|276,0:73|277,0:167,727,789|279,0:97,443|280,0:95|281,0:57|282,0:90,175|284,0:76,360|285,0:90|287,0:103,164|288,0:76|289,0:113,226,452,597|290,0:103|292,0:98|293,0:378|294,0:82|295,0:281|296,0:173,199|297,0:305,647,997,1043|298,0:88,121,152,176,200|299,0:79|301,0:51|302,0:83,193,528,847,1209,1302,1431,1516|303,0:38|304,0:57,66,204|305,0:33,296,341,410,427,606|306,0:878|307,0:265,308,395,444,472,630,649,836,1084,1127|308,0:368,563,709|309,0:132,388,461,558,681|310,0:190,331,449|311,0:309,414|315,0:1428,1826,1892,2177,2572,2751,3065,3658,3800|317,0:229,816|318,0:416,808,891,1130|319,0:1001|320,0:657,832,960,1870,2073,2531|321,0:491,2111,2149,2289|322,0:461,463|324,0:532,586,804,885,978,1111,1338|325,0:205,263|326,0:709,860,939,1161|327,0:476|328,0:466,537|329,0:100|330,0:290,465,715|332,0:315|365,0:91,139|366,0:333,446,1298|367,0:542|369,0:254,345|372,0:289,1029|375,0:808,1163|382,0:389|389,0:207|393,0:2325|396,0:950,1175|397,0:816|405,0:655|410,32:73|411,32:97,346|412,0:299|413,0:75,369,457|414,0:92|415,0:64|416,0:49,157|417,32:103,142|418,32:269|419,0:460,505|420,32:105,174,342|421,32:171,427|422,32:40,143|423,32:143,169,194|424,0:66,420,652,724,925|425,32:164,236,348,435|426,32:112,146,217,296,426|427,32:43,63,161|428,32:148|429,32:60,132|430,32:128,215,421|431,0:565,666,1164,1215|432,32:140,316,347,636|433,32:195,302,340|435,32:179,304,521,645|436,0:355|438,0:42|439,0:89|441,0:382,908|442,0:400|443,32:416,568|444,0:201,772|445,0:412,943|446,0:260|447,0:215,321|448,0:147,1230|449,0:54,1100|450,0:95,103,113,368|451,0:123,1166,3262|453,0:236|454,0:434,1060|456,0:925|457,0:642|459,0:69,138|460,0:260,391|461,0:122|462,0:115|464,0:540,570,946,1024,1254,1942,2078,2303,2498,2514,2538,2589,2784,2801,3032,3403,3526,3764,3940,4110,4196|467,0:803,958,1062|472,0:115|473,0:110,169|474,0:898|477,0:79,158|478,0:82,404|479,0:83,122|480,0:117|482,32:345,466,578,600,652,1319|484,32:270,371|495,0:181|496,0:278,470,529,559,614,647,688,870,1136|505,0:126|509,0:114|513,0:1164,1167|515,0:83|520,0:397,778,781,800|522,0:276|525,0:446|527,0:280|532,0:286|542,0:289|544,0:402,998|545,0:186|546,0:438|551,0:69,118,179|552,0:103|554,0:135|557,0:382|559,0:141,169,635,686,2349|560,0:1231|561,0:1186|562,0:506,727,864|563,0:471|564,0:322,518,793,864|565,0:235,418,527,601,687,748,783|567,0:782|568,0:261,309,407|569,0:405,1998,4016,4934|570,0:41,360,472,591|571,0:102|572,0:532,610,729|574,128:7,15,41,187,231,375,536|575,0:184|576,0:131,292|577,0:97,117,293,365,878,899,979,997,1125,1297,1317|578,0:161,342,479,482,532,610,858|579,0:263,1730,1732,1842|580,0:2654,2715|584,0:279|586,0:1334,1508|587,0:124,126,160|589,0:268|590,0:189,263,679,973|597,0:115,190,876,1481,1517,2078,2273,2453,2686,2799|598,0:34,82,97,362,389,467,619,957,1093,1171,1182,1373,1467,1485,1501,1562,1581,1608,1652,1672,1809,1835,1910,1935,2034|599,0:66,81,185|602,0:127,172,212|603,0:131,357,433,601,742,773,817,1422,1595,1622,1970,2087,2110,2364,2445,2493,2682|604,0:237,443,521,681,730,875,904,944,1779,2053|605,0:388,438,551,582,632,1505,1919,1926,2312,2444|606,0:121,567,745,784,909,963,1015,1436,1457,1470,1506,1681,1705,1752,2049,2073,2231,2266,2288,2299,2559,2590,2622,2906|607,0:247,273,422,856,905,1005,1036,1080,1634,1862,1903,2767,3209,3428,3461,3496,3515,3560|608,0:275,325,403,443,493,947,979,1090,1646,1778|609,0:1816,2044|610,0:90,96,403|611,0:230|612,0:77,188,196,230,352,357,395,1152,1215|613,0:99,115,164,254,308,382,1249,2097,2277,2377,2671,2726,2731,2759,2785,3392|614,0:114,141,157,521,858,951,1028|615,0:97|616,0:197,325,352,622,645,701,1174,1222,1294|618,0:158,183,268,623,673,1109,1156,1208,1273|619,0:775,1148|620,0:89,146,201,321|621,0:89,233,404|622,0:124,169,330,468,490,667,980,1477|623,0:224,1570,1588|624,0:359|626,0:157,541|627,0:197,377|630,0:32,347,405,428|633,0:64|635,0:263,439|636,0:185|639,0:83,106|641,0:188|642,0:307|647,0:313"/></pk>