<?xml version="1.0" encoding="UTF-8" standalone="no"?>
<pk><wd nm="uery_all" rd="85,0:216,283,627|123,0:44"/><wd nm="uery_cache" rd="324,0:817"/><wd nm="uery_cache_entries" rd="324,32:135,433,456,981,1168,1274,1381|329,0:1679"/><wd nm="uery_cache_mode" rd="324,32:163,719,735,1019,1194,1300,1407|329,0:1713"/><wd nm="uery_cache_size_in_pages" rd="324,32:185,1424,1449|329,0:1739"/><wd nm="uery_convert" rd="59,0:2864,2970,3095,3554"/><wd nm="uery_editor" rd="49,0:488|58,0:566|61,0:607,657,1421,1501,2283,3965|65,0:246|248,0:689|315,0:222|316,0:1034"/><wd nm="uery_editor_1" rd="59,0:2608,2835,2950"/><wd nm="uery_editor_2" rd="59,0:2628"/><wd nm="uery_editor_3" rd="59,0:2648"/><wd nm="uery_editor_4" rd="59,0:2668"/><wd nm="uery_editor_5" rd="59,0:2688"/><wd nm="uery_editor_cub_cas_1" rd="249,0:1471"/><wd nm="uery_editor_cub_cas_2" rd="249,0:1521"/><wd nm="uery_editor_cub_cas_3" rd="249,0:1571"/><wd nm="uery_editor_cub_cas_4" rd="249,0:1621"/><wd nm="uery_editor_cub_cas_5" rd="249,0:1671"/><wd nm="uery_editor의" rd="61,0:1519"/><wd nm="uery_result" rd="86,0:110,294,314,374,430|87,0:125,313,333,426,485|88,0:233,253,313,365|120,0:373|130,0:118,190,209,229|131,0:82,101,125,174,208|132,0:96,167,186,206|133,0:104,178,197,217"/><wd nm="uery_result_" rd="133,0:152"/><wd nm="uery_result_err_msg" rd="86,0:189,615|87,0:178,662|130,4:0,24,166"/><wd nm="uery_result_free" rd="86,0:229,642|87,0:218,689|88,0:167,539|131,128:0,21,61,280,406"/><wd nm="uery_result_result" rd="86,0:166,568|87,0:155,615|88,0:128,475|132,4:0,23,144"/><wd nm="uery_result_stmt_type" rd="86,0:140|88,0:102,510|133,4:0,26"/><wd nm="uery_sec" rd="302,0:1028"/><wd nm="uery_spec" rd="120,0:1289|223,0:514,536|385,128:0,14,232|408,0:211"/><wd nm="uery_spec&apos;" rd="378,0:926"/><wd nm="uery_spec_class_of" rd="378,0:942"/><wd nm="uery_specification" rd="645,0:414,441,670"/><wd nm="uery_specs" rd="375,0:702"/><wd nm="uery_statement" rd="439,0:176,264,295|440,0:117,233"/><wd nm="uery_time" rd="29,0:931|61,0:762,1164,1787,2550,2575,2922,3493,4267|297,32:656|302,0:311,354|315,32:3576,3591|316,0:744|330,32:812,834,952|331,0:222,1057"/><wd nm="ueryspec" rd="375,0:723"/><wd nm="uery 2" rd="649,0:115"/><wd nm="uery 2 select" rd="648,0:305"/><wd nm="uery select" rd="647,0:517"/><wd nm="uery가" rd="243,0:2550"/><wd nm="uery를" rd="243,0:2527"/><wd nm="uery와" rd="77,0:98"/><wd nm="uer와" rd="11,0:5599"/><wd nm="ues" rd="59,0:1527,1618|151,0:203|152,0:178|156,128:0,9,57,133,309,422|157,0:241,543,573|160,0:201|162,0:186|163,0:210|166,128:0,9,40,65,95,192,304,317,423|168,0:166|172,0:1526|175,0:648,699,1640,1754,2127,2173,2219,3121,3167,3213|182,0:161|186,0:288|191,0:607|197,0:224|198,0:406|200,0:295|205,0:968|214,0:344|217,0:217,466|221,0:232|236,0:1938,2033|237,0:1441|241,0:1540|246,0:1516|320,0:1291,1344,1486,1527,1598|348,0:127,176,298,338|351,16:860,888,908,950,1080,1110,1143,1331,1376|364,0:2227|384,0:185|404,0:231,649,658,1328|440,0:36,101,355|441,0:96,139,669,813|443,0:628|444,0:352|453,0:789|474,0:980,1052,1116,1163,1222,1279,1326,1362,1410,1457|482,0:1411,1445,1479|542,0:501,537,593,630,668,703|544,0:119,170,506,551,599,747,798,848,897,939,1086,1193,1237,1285|545,0:289,333,381|546,0:252,565,609,657,761,792,944|547,0:231,300,721,759,837,869,902,938|549,0:260,304,352,410,461|551,0:420,457|552,0:222,266,314,372,423,472,521|554,0:307,345,385,425,465,506,549|555,0:175,431|556,0:121,169,604,642,666,724,764,805,848,927|558,0:253,595,633,728,766,915|574,0:317|579,0:646,677,927,1512,1775|580,0:526,548,581|603,0:1046,1480,1687|604,0:1172,1590,2152|605,0:923,980,1037,1094,1151,1672,1729|606,0:1230,1579,1862,2142|607,0:1312,1720,2928|608,0:748,1154|612,0:667,748,829,1581|621,0:289,656|622,0:1172,1282"/><wd nm="uest" rd="80,0:76|125,0:106|135,0:57|190,0:290|192,128:0,20,42,109,364,525|195,0:358|196,0:359|197,0:242|198,0:425|199,0:338|200,0:314|205,0:573,837,1129|206,0:567|210,0:305|214,0:387|215,0:302|216,0:417|217,0:423|218,0:622,948|219,0:259|221,0:250|222,0:287|224,0:252|243,0:1272,1411,1550,1677,1808,2029,2093,2116,2138,2159,2180,2202|302,0:466,549,745"/><wd nm="uest_handle" rd="205,0:205,369,550"/><wd nm="uest_sec" rd="302,0:924"/><wd nm="uester" rd="613,0:510"/><wd nm="ueue" rd="29,0:857|61,0:688,1090,1546,2848,3419,4193"/><wd nm="ue         don&apos;t" rd="234,0:306"/><wd nm="ue는" rd="328,0:470"/><wd nm="ue만" rd="220,0:159"/><wd nm="ue에" rd="220,0:97"/><wd nm="uf" rd="77,0:252,389|78,0:122,211|79,0:136,180|81,0:75,135,196,330,379|82,0:476,553|83,0:136,160|84,0:217,281|85,0:553,671|86,0:338,393,522|87,0:357,451,565|88,0:277,332,429|89,0:102,125|91,0:227,250|94,0:211,293|96,0:161,189|98,0:302,363|99,0:115,154,182|108,0:61,139,154,213,223|109,0:120,164|110,0:188,263|111,0:132,176|112,0:187,202,277,287|113,0:113,182|114,0:182,262|115,0:179,194,268,279|116,0:107,165|117,0:181,241|118,0:183,198,273,283|120,0:128|123,0:275,311|124,0:225,332|125,0:256,307|126,0:120,153,189,217,226|127,0:267,338|128,0:463,548|129,0:547,646|131,0:272|134,0:146,226,345,432|135,0:1858,2006|136,0:130,217,287|137,0:139,238,325|138,0:134,230,312|139,0:110,199,273|140,0:189,249|141,0:114,203,280|145,0:371,434"/><wd nm="uf_len" rd="126,0:130,204"/><wd nm="uf_size" rd="99,0:125,168"/><wd nm="ufacturing_site" rd="346,0:426"/><wd nm="uffer" rd="41,0:634,719|45,0:1759,1797|51,0:364,400,689,784,1703|112,0:94|115,0:88|118,0:91|236,0:479,516,560,593,682,722,759,788,818,842,1675,1862,2169,2248|240,0:785,2072,2152|302,0:615|329,0:3119,3210,3305|464,0:2141,2241,5401"/><wd nm="uffer_clear" rd="90,128:0,22,71,234"/><wd nm="uffer_page_read" rd="302,0:628"/><wd nm="uffer_page_write" rd="302,0:667"/><wd nm="uffer_pages" rd="11,0:3013,3035|322,32:131,354,370,423,560,614|323,32:96,122,156,270,287,345,477,565,619,699,726,823,840|329,0:646,709,746,1544,3130,3176,3221,3275,3316,3358"/><wd nm="uffer_pages에도" rd="11,0:3052"/><wd nm="uffers" rd="464,0:5300"/><wd nm="ugoslav" rd="569,0:5162"/><wd nm="uguay&apos;" rd="560,0:1551"/><wd nm="ui" rd="231,0:41|237,0:576|248,0:130|252,0:16|256,0:342|262,0:48,189"/><wd nm="uid" rd="243,0:2626"/><wd nm="uide" rd="329,0:2619,4333"/><wd nm="uild" rd="438,0:182,246,503,533"/><wd nm="uinea" rd="515,0:469"/><wd nm="uire" rd="445,0:721,904"/><wd nm="uire_write_lock" rd="464,0:4909"/><wd nm="uired" rd="3,0:466|329,0:3396"/><wd nm="uired_page_id" rd="25,0:694"/><wd nm="uis" rd="560,0:1620|569,0:2255"/><wd nm="uit" rd="3,0:598|7,0:5702|45,0:2305|48,0:729"/><wd nm="uiv" rd="243,0:258|246,0:174,1251"/><wd nm="ui로" rd="268,0:394"/><wd nm="uj" rd="247,0:1098"/><wd nm="uk" rd="622,0:1296,1537,1592"/><wd nm="ukr&apos;" rd="569,0:5114"/><wd nm="ukraine" rd="569,0:5119"/><wd nm="ul" rd="7,0:2200,2633|175,0:1047|236,0:2461,2495,2529,2568,2605,2643,2819,2853,2887,2926,2963,3001|474,0:987|476,0:394|479,0:536|480,0:575|517,0:397|544,0:910|552,0:534|568,0:1306,1365"/><wd nm="ul&apos;" rd="552,0:769|569,0:5623"/><wd nm="ul_1988_soccer" rd="578,0:837,1037,1144"/><wd nm="ul_count" rd="86,0:596|87,0:643"/><wd nm="ular_expression" rd="464,0:5349"/><wd nm="ularity" rd="247,0:655|261,0:210|614,0:31"/><wd nm="uld" rd="236,0:291"/><wd nm="uld_not_acquire_write_lock" rd="464,0:4909"/><wd nm="uld_not_allocate_search_buffers" rd="464,0:5300"/><wd nm="uld_not_compile_regular_expression" rd="464,0:5349"/><wd nm="uld_not_reset_working_buffer" rd="464,0:5401"/><wd nm="ule" rd="341,16:2206,2216,2231,2241,2276,2316|364,0:1199|580,0:1628,1639,1650,1667,1704,1741|597,0:328,354"/><wd nm="ules" rd="245,0:557|597,0:303"/><wd nm="uliagmeni" rd="619,0:703,1047"/><wd nm="ull" rd="3,0:445,552|7,0:2131,2662|23,0:431,444|31,0:1656|54,0:121,201,284,365|73,0:183,215,232|74,0:181,218,237,261,719,741,746|77,0:337|78,0:207|82,0:90,110|97,0:778,795,801,829,871,879|100,0:93,341|101,0:151|102,0:115,174|103,4:49,127,162,292|104,0:102|105,0:117|106,0:107|107,0:102|120,0:298,598|127,0:147|128,0:84,794|130,0:131|132,0:109|133,0:117|135,0:504,519,1912,1933|144,0:433|146,0:788|175,0:1543,5860|191,0:251,255|193,0:248|207,0:346|223,0:619,627,789,797|236,0:4223|241,0:550,567,582,1057,1321,1338,1808|242,0:425|317,0:114|318,0:145,203|319,0:127,170|326,0:1098,1178,1252|329,0:477,945,1009,1061,1115|333,16:251,660,688|335,0:1949|337,0:111|341,0:2610|364,0:927,1234|372,0:380,478,559,567,709|375,0:1024|377,0:318,486|381,0:166|382,0:203,291|384,0:125,248|388,0:348|393,0:305,388,683,742,750,853,1952,1972,1990,2008,2030|394,0:1614|396,0:513,587|402,0:204|403,0:233,321|404,0:285,754,776,1419|407,0:186|408,0:898,972|431,0:1035|441,0:310,509|443,0:260|444,0:849,866|448,0:1195,1418,1435,2154,2171,2236,2633,2650|449,0:438,455,470,953,1105|456,0:934,1221|464,0:1241,4503,4551|466,0:927|468,0:93,390,762|469,0:235,251,268|472,0:110,175,219,239,245,297,379,391,431,465,546,558|473,0:33,96,114,153,173,196,224,254,286,297,381,397|474,0:329,849,862|482,0:470,491|485,0:141,157,250,256,333,339|486,0:132,261,270|487,0:86,122,131|492,0:272,308,317|493,0:185|495,0:969,987|513,0:286,1039,1043,1072,1086,1106,1158,1187,1208|514,0:132,175,181|515,0:175,212,222|517,0:198,241|519,0:122,357,388,406|520,0:213,694,706|521,0:116,150,159|522,0:86,98,122,293,302,323,332,385,394|523,0:95,117,185,194,242,251|524,0:147,200,206|525,0:284,387,393|526,0:119,151,188,266,275,311,320,409,418|527,0:87,99,123,297,306,327,336,389,398|528,0:95,117,187,196,244,253|529,0:101,125,134,268,298,317|530,0:205,253,262,600,611,632,671,694|531,0:149,172,193,268,277,362,371,403,412|532,0:156,215,369,375|533,0:116,150,159|534,0:401,444,561,570,608,617,1941,1983,2027,2036,2095,2104|535,0:151,194,300,309,384,393|536,0:171,214,324,333,415,424|537,0:135,170,335,344,405,414|538,0:150,193,299,308,351,360|539,0:176,219,330,339,382,391|542,0:467,709|544,0:982,1016,1047,1107,1325|556,0:889,933,977|559,0:227,1478,1646,1661,1673,1686,1699,1710,2106,2121,2133,2146,2159,2170,2613,2628,2641,3018,3033,3045,3058,3071,3082|560,0:201,417|563,0:743,773|569,16:49,336,5218,5227,5242,5268,5313,5327,5336,5436,5538,5853,5885,5914|579,0:1344|580,16:11,52,60,82,119,154,206,256,860,890,991,1011,1033,1050,3009,3056,3107,3130|581,0:430,534,1018,1137,1174,1199,1222,1245|586,0:923,1013|591,0:767|604,0:2281,2294|623,0:1092,1137|645,0:569,626"/><wd nm="ull&apos;로" rd="372,0:574|393,0:757"/><wd nm="ull_first" rd="623,0:1025"/><wd nm="ull_ind" rd="74,0:192,610,709"/></pk>