<?xml version="1.0" encoding="UTF-8" standalone="no"?>
<pk><wd nm="설치되어야" rd="253,0:880|261,0:407"/><wd nm="설치된" rd="1,0:190|232,0:294|235,0:615|242,0:178,422,788,927|244,0:128|246,0:289|249,0:2049|253,0:122|262,0:171|265,0:56|322,0:504"/><wd nm="설치된다" rd="244,0:106|250,0:445"/><wd nm="설치를" rd="245,0:473|249,0:359"/><wd nm="설치에" rd="33,0:807|329,0:277"/><wd nm="설치에서" rd="454,0:454,1092"/><wd nm="설치와" rd="238,0:151|249,128:8,21,2747|250,128:10,25,908"/><wd nm="설치하고" rd="249,0:2360|250,0:102"/><wd nm="설치하기" rd="249,0:54"/><wd nm="설치하는" rd="618,0:870"/><wd nm="설치하려는" rd="13,0:387|20,0:436"/><wd nm="설치하려면" rd="250,0:338"/><wd nm="설치하면" rd="249,0:2626|253,0:64"/><wd nm="설치하면서" rd="253,0:464"/><wd nm="설치하여" rd="618,0:825"/><wd nm="설치하였다면" rd="188,0:120"/><wd nm="설치하지" rd="242,0:975"/><wd nm="설치한" rd="249,0:1059|253,0:953,1126|317,0:213"/><wd nm="설치한다" rd="33,0:797|249,0:228|250,0:133"/><wd nm="설치할" rd="242,0:165|249,0:232,353,2064,2593|250,32:267,325"/><wd nm="설치해도" rd="244,0:122"/><wd nm="설치해야" rd="250,0:302"/><wd nm="섭" rd="598,0:587"/><wd nm="섭받지" rd="321,0:505"/><wd nm="섭을" rd="598,0:613|602,0:103,124"/><wd nm="섯" rd="628,0:381,405"/><wd nm="성" rd="0,0:65|3,0:63|4,0:848,913,972,1015|5,0:59|6,0:563,1074,1114|7,0:1086,1124,1509,1526,3181,3234,3309,3378,3818,4442,4614,5361|10,128:6,17,318,413,560,889|11,128:6,14,2329,2437,2479,2559,3345,6097|12,0:117|18,0:51|20,0:508|25,0:204,370|26,0:646|27,0:131|29,32:36|31,128:7,18,501,691,2195|33,0:1061|34,32:687,1604,2022,2236,2325,3117|36,32:309,362,511,779,1429|37,32:336,731,952|38,0:201|41,0:190,440,933,1077,1454|45,0:260,268,305,493|47,0:457,465,502,1225,1710,1797|48,0:287|49,0:744,754|52,0:670,766,1385|53,0:619|54,0:77|68,0:124,804|71,0:374,620,678|77,0:39,308|78,0:178|101,0:88,327|125,0:30,303|127,0:39,314|128,0:510|135,0:298,1569,1637,1927|136,0:42,75,273|137,0:46,78,294|138,0:40,76,286|139,0:35,58,255|141,0:37,60,259|151,0:74|163,0:69|172,32:28,34,419,1107|184,128:2,7,26,690|187,128:21,44,529|188,128:5,18,31,139,183,256,382,437,659|189,0:210,264|193,0:203|194,0:193|218,0:455,472,1473|219,0:297,302,375,527,551,586,853|223,0:319|226,0:217|227,0:205|228,0:202|229,0:212|235,0:486|237,16:13,179,310|238,0:121,198,211,229,242|239,16:143,753|242,0:258,307|243,0:59,2574|251,16:166,1119|252,16:1397,1647|256,128:3,8,90,539|257,0:468|259,0:691|260,32:190,421,537,797,886,965,969,1024,1091,1168,1408|261,0:32,44,58,70,166,178,342,867,886,1392,1396,1550,1826|263,0:291|264,32:20,530|267,0:74|268,32:63,173,258,277,313,349,389,454|269,32:911|270,128:6,14,45,64,801,1062,1389,1558|271,0:129|272,0:556,571|277,0:544,559|283,32:221,327|287,0:107,168,356|289,0:492,505,529,1401|294,0:458|297,0:1047|298,0:278|302,0:391|303,128:0,4,597|305,32:74,248|306,32:127,174,291,1039|307,0:361|308,0:492|310,0:194|311,32:222|318,0:413,567,1029|319,0:1116,1187|320,0:2314,2664,2688,2752|321,8:0,9,30,495,1226|322,0:654,784,806,835|323,0:661,1220|328,16:121|329,0:79|330,128:6,1154|331,16:253|363,16:9,540|365,0:124,215|369,0:37,193,218|370,0:271,282|371,0:139,176|372,0:285|375,0:500,539,578|377,0:85|379,0:176|382,0:367|383,0:34|390,128:7,17,368|391,0:237,314,329|392,0:26|393,0:53|394,0:68,1133,1398|399,0:216|412,128:3,8,410,673|413,128:3,8,804,1084|419,128:3,8,98,842|424,128:3,8,451,1034,1048,1073,1290|431,128:3,8,459,1575|436,128:3,8,378,532,699|438,0:32,52|441,0:399,617|448,0:137|450,0:304,404,407|455,128:12,28,75,256,929|460,0:411|461,128:7,16,174,176,410,567|462,128:0,3,6,252,329,513,661|464,0:1284,3892|474,0:524,804|477,0:315|484,0:329|534,0:743,963,1211,2119|541,0:119,238,244|543,0:279|554,128:14,30,181,880|560,0:1750|572,128:6,11,1241|575,0:240,244|576,0:32|577,0:142,937|579,16:74,1068|580,0:1256,2590|583,0:553|586,0:1348|588,0:94,244,397|590,128:3,9,56,61,66,73,96,234,272,319,381,403,627,666,700,728,750,777,813,874,948,1112|597,0:474,489,595,615,990,1020,1129,1161,1416,1955,1978,1988,2059,2152,2176,2206,2231|598,128:6,15,208,230,330,530,633,648,733,2192|602,0:44|603,0:359|604,0:445|608,0:34|609,0:771|613,0:199,434,2779|617,0:84,411|618,0:145,193,389,888|619,0:426|620,0:25|623,0:954,1191|624,0:674|627,0:325,338,395|631,0:661|644,128:10,24,977"/><wd nm="성/잠금" rd="321,128:2434"/><wd nm="성 값을" rd="128,0:41"/><wd nm="성값에" rd="627,0:362"/><wd nm="성값을" rd="627,0:427,484"/><wd nm="성격상" rd="467,0:492"/><wd nm="성공" rd="7,0:598,3960|32,0:753|34,0:675|80,0:251|85,0:694|100,0:324|123,0:334|125,0:330|129,0:669|135,0:2029|190,0:161|191,0:529|192,0:159|193,0:210|194,0:200|195,0:151|196,0:151|197,0:173|198,0:282|199,0:210|200,0:171|201,0:140|205,0:632|206,0:196|207,0:323|208,0:160|210,0:214|211,0:168|212,0:173|214,0:245|215,0:134|216,0:242|217,0:417|220,0:387|221,0:181|222,0:196|223,0:324|224,0:161|225,0:227|226,0:270|227,0:257|228,0:231|229,0:241|278,0:469|392,0:192|580,0:565"/><wd nm="성공적으로" rd="85,0:444|123,0:151|135,0:42|218,0:87|246,0:1694|464,0:347,1732,1974,2853,3256,3417,3753,3929,4085,4379"/><wd nm="성공하고" rd="85,0:385"/><wd nm="성공하면" rd="252,0:904|299,0:111|464,0:2978"/><wd nm="성공하여" rd="617,0:178"/><wd nm="성공한" rd="85,0:423"/><wd nm="성공한다" rd="580,0:437|603,0:2320"/><wd nm="성공할" rd="2,0:1319"/><wd nm="성과" rd="31,0:899,916,1106|38,0:939|175,0:539|223,0:96|332,0:319|376,0:213|393,0:1741|394,0:1367|450,0:300|460,0:427,453|461,0:50|576,0:301|577,32:135,230,545,684|583,0:320|584,128:0,8,58,463|585,128:3,15,583|586,0:45|587,0:38|590,0:982|597,0:1580|599,0:30"/><wd nm="성능" rd="8,0:457|32,0:3518|37,32:23,45,162,251,281,524|47,0:2414|49,32:707,715,765,778,981|58,0:78|237,0:394|252,0:193|261,0:603,1791,1830|296,0:105|313,128:0,7,267|324,0:606|325,0:30|326,0:908|541,0:106,192,208|549,0:864|551,0:123"/><wd nm="성능과" rd="313,0:55|329,0:251|332,0:170"/><wd nm="성능상" rd="47,0:178"/><wd nm="성능상의" rd="240,0:469"/><wd nm="성능에" rd="237,0:398|313,0:11|320,0:2391,2627|564,0:40"/><wd nm="성능으로" rd="32,0:161"/><wd nm="성능을" rd="8,0:1551|32,0:3567|35,0:141|37,0:90|38,0:1264|246,0:1111|261,0:779,1399|325,0:301,539|563,0:395"/><wd nm="성능이" rd="34,0:2893|261,0:2465|318,0:756|320,0:2735|322,0:488"/><wd nm="성도이다" rd="260,0:47"/><wd nm="성되고" rd="52,0:558|261,0:1430"/><wd nm="성되는" rd="4,0:239|8,0:920,1266|11,0:1589,1794,2294,2669,3653,4461,4585|26,0:1437|27,0:409|30,0:375|31,0:979|34,0:2067,2268,2355,3168|49,0:761|59,0:1413|241,0:123|246,0:125|260,0:1119,1843|264,0:222|275,0:436|315,0:2879|316,0:826|318,0:538,998|327,0:758,800|329,0:2340|331,0:435|561,0:1043|562,0:105|569,0:6348|572,0:333"/><wd nm="성되는데" rd="562,0:79|563,0:619|619,0:405"/><wd nm="성되도록" rd="34,0:1848,1956,2283,2370"/><wd nm="성되며" rd="31,0:107|252,0:1522,1570|260,0:1614|264,0:424|295,0:51|296,0:45|332,0:60|562,0:244"/><wd nm="성되면" rd="7,0:1570|260,0:119|571,0:47"/><wd nm="성되어" rd="48,0:135,773|85,0:208|93,0:81|129,0:94|252,0:125|262,0:201,234|264,0:112,151,203,343|268,0:71|269,0:790|270,0:75|287,0:289|301,0:26|302,0:859,1310,1327|307,0:456|312,0:555|371,0:207,245|372,0:62|373,0:46|375,0:48|377,0:46|378,0:43|379,0:52|380,0:54|381,0:59|382,0:54|383,0:54|384,0:55|385,0:57|386,0:69|387,0:81|474,0:894|569,0:4984|614,0:137|623,0:59"/><wd nm="성되어야" rd="11,0:3785|31,0:554|47,0:75"/><wd nm="성되었고" rd="7,0:7190"/><wd nm="성되었는데" rd="375,0:1193|396,0:1207"/><wd nm="성되었다" rd="240,0:143|258,0:388|577,0:1052"/><wd nm="성되었다고" rd="614,0:157"/><wd nm="성되었을" rd="7,0:728|513,0:913|562,0:337|625,0:243"/><wd nm="성되지" rd="260,0:2026|270,0:1042|318,0:432|570,0:786|572,0:924|605,0:519|608,0:372"/><wd nm="성되지만" rd="370,0:172"/><wd nm="성된" rd="2,0:1079,1365,1430,1446,1462,1492,1510|4,0:900|5,0:52|6,0:539,552,969|7,0:4929|32,0:530,803,867,933,996,1365,1410,2660,2975,3176|33,0:517,739,1171|36,0:424,872|53,0:526|59,0:394,2395,2489,2736|83,0:44|85,0:373|172,0:168,190,400,991,1031,1114|174,0:48|205,0:91|214,0:247|218,0:220|219,0:1147|253,0:1219|260,0:2074|261,0:335,2209|283,0:417|285,0:511|298,0:302|318,0:1090|322,0:843|324,0:326|369,0:349|375,0:781|398,0:44|399,0:52|404,0:1144|459,0:66,155|474,0:484|520,0:422|541,0:391|554,0:63|565,0:569,632|569,0:4561|579,0:119|585,0:225|588,0:164|594,0:40|623,32:154|644,0:340"/><wd nm="성된 데이터" rd="32,0:1454"/><wd nm="성된 질의" rd="59,0:3012"/><wd nm="성된다" rd="2,0:1125|4,0:279|7,0:1313|8,0:1242|11,0:1645,1845,1894,2253,4269,4432|19,0:516|34,0:974,1147,1753,2123|38,0:1220|41,0:122|42,0:105,240|47,0:2068|53,0:945|55,0:736,808|59,0:364,1407|240,0:395|251,0:1203,1357|252,0:1497|255,0:80|256,0:57|261,0:923,1042|265,0:147|266,0:116|295,0:480|301,0:75|305,0:396,501|314,0:47|315,0:54,1202,2929|329,0:74|332,0:233|370,0:47|483,0:147|484,0:618,718|541,0:380|561,0:931|570,0:720,750|572,0:95,858,888|585,0:89|618,0:133|620,0:169"/><wd nm="성된다고" rd="2,0:1024"/><wd nm="성될" rd="3,0:43|8,0:340,603|11,0:575,760,819,907,1165,4336,4410|14,0:474|22,0:516,606|23,0:777,1574|32,0:706|34,0:1118,1431|267,0:27|274,0:224|292,0:201|460,0:225|484,0:48|520,0:293|562,0:939"/><wd nm="성됨" rd="430,0:359,435|432,0:581,649|433,0:583,636|435,0:395,457,535"/><wd nm="성됩니다" rd="47,0:916"/><wd nm="성들" rd="378,0:216|588,0:153,186"/><wd nm="성들과" rd="590,0:422,483,542"/><wd nm="성들에" rd="597,0:35"/><wd nm="성들을" rd="220,0:134"/><wd nm="성들의" rd="220,0:53|578,0:1484"/><wd nm="성들이" rd="597,0:554"/><wd nm="성립된다" rd="456,0:760"/><wd nm="성립하면" rd="477,0:138"/><wd nm="성만으로는" rd="579,0:1639"/><wd nm="성만을" rd="189,0:178|474,0:750|520,0:61"/><wd nm="성명" rd="236,0:4140|364,0:41|372,0:68,501|373,0:52|374,0:32|375,0:54|376,0:82|377,0:52|378,0:49|379,0:58,124|380,0:60|381,0:65|382,0:60|383,0:60|384,0:61|385,0:63|386,0:75|387,0:87|388,0:20,333|389,0:14|393,0:62,91|394,0:125,154|395,0:50|396,0:51|397,0:90|398,0:60|399,0:69|400,0:67|401,0:120|402,0:69|403,0:57|404,0:61|405,0:78|406,0:91|407,0:68|408,0:61"/><wd nm="성명이" rd="372,0:446|393,0:359,2337"/><wd nm="성문에 맞추어" rd="563,0:691"/><wd nm="성별" rd="569,0:898,3559|644,0:718|647,0:290"/></pk>