<?xml version="1.0" encoding="UTF-8" standalone="no"?>
<pk><wd nm="2009년" rd="35,0:251"/><wd nm="200e" rd="425,0:631"/><wd nm="200kb" rd="329,0:3353"/><wd nm="200명" rd="562,0:729"/><wd nm="200이" rd="562,0:819"/><wd nm="201" rd="247,0:527"/><wd nm="2012" rd="603,0:1486,1693,1793,1802,2242,2251|604,0:2158,2298|607,0:1602,1726,2134,2286,2418,2496,2934,3132,3376"/><wd nm="2014e" rd="425,0:246"/><wd nm="202368236335337e" rd="505,0:380"/><wd nm="20281" rd="560,0:714,745,776,807"/><wd nm="20283" rd="560,0:652,683"/><wd nm="203" rd="49,0:208,667|59,0:412,489,570,661|562,0:1087"/><wd nm="20326" rd="560,0:838"/><wd nm="20328" rd="560,0:867"/><wd nm="20331" rd="560,0:893"/><wd nm="2038년" rd="419,0:268,317|421,0:251,303"/><wd nm="2048" rd="11,0:2901|270,0:348"/><wd nm="2048000" rd="7,0:6975"/><wd nm="205" rd="249,0:1411|562,0:1111"/><wd nm="2052370e" rd="505,0:468"/><wd nm="2062746055483e" rd="505,0:336"/><wd nm="2088" rd="236,0:2431,2789"/><wd nm="208의" rd="433,0:440"/><wd nm="20개의" rd="569,0:936"/><wd nm="20까지" rd="323,0:1070"/><wd nm="20분" rd="322,0:320"/><wd nm="20의" rd="213,0:309"/><wd nm="21" rd="7,0:2203,2636|29,0:802|31,0:461,1959,1983,2010,2034,2061|61,0:1034,2792,3363,4012,4137|248,0:734|559,0:2707|621,0:324"/><wd nm="210" rd="249,0:1449|560,0:844"/><wd nm="210.192.33" rd="315,0:2013"/><wd nm="210.194.34" rd="315,0:2025"/><wd nm="210.211.133.100" rd="198,0:314|200,0:203"/><wd nm="210.216.33.250" rd="173,0:319|175,0:887,2312,3301,4632,5478"/><wd nm="2104" rd="509,0:253"/><wd nm="210547196874904e" rd="505,0:292"/><wd nm="211" rd="249,0:1499"/><wd nm="211.133.100" rd="198,0:314|200,0:203"/><wd nm="212" rd="249,0:1549"/><wd nm="213" rd="249,0:1599"/><wd nm="214" rd="249,0:1649|562,0:1127"/><wd nm="2147483647까지이다" rd="427,0:140"/><wd nm="2147483648에서" rd="427,0:128"/><wd nm="2149" rd="49,0:500"/><wd nm="215" rd="560,0:1691"/><wd nm="216.33.250" rd="173,0:319|175,0:887,2312,3301,4632,5478"/><wd nm="2161" rd="49,0:537"/><wd nm="217" rd="249,0:1699"/><wd nm="21이라는" rd="31,0:1894"/><wd nm="22" rd="31,0:473|151,0:435|191,0:727|205,0:1088|217,0:586|248,0:624|249,0:1737|372,0:856|508,0:455"/><wd nm="22,18" rd="612,0:763"/><wd nm="22,3" rd="151,0:440"/><wd nm="2203" rd="49,0:208,667"/><wd nm="222" rd="249,0:1737"/><wd nm="22203" rd="49,0:208,667"/><wd nm="223" rd="249,0:1782"/><wd nm="223,372,036,854,775,807이다" rd="422,0:110"/><wd nm="223,372,036,854,775,808에서" rd="422,0:83"/><wd nm="224" rd="249,0:1827"/><wd nm="225" rd="249,0:1872|560,0:873"/><wd nm="2250738585072014e" rd="425,0:246"/><wd nm="226" rd="249,0:1917|562,0:1103"/><wd nm="227" rd="59,0:341"/><wd nm="229" rd="249,0:1962"/><wd nm="22를" rd="422,0:348|427,0:328"/><wd nm="23" rd="31,0:485|53,0:853,874,895,916|64,0:383|249,0:1782|317,0:95,200,222,242|329,0:450,4444|372,0:865|388,0:59,318,528,725|389,0:35|400,0:1392|434,0:79|522,0:450,473|523,0:297,322|527,0:455|528,0:327|531,0:77,474|534,0:889|537,0:516,574"/><wd nm="23,372,036,854,775,807이다" rd="422,0:110"/><wd nm="23,372,036,854,775,808에서" rd="422,0:83"/><wd nm="23.45" rd="537,0:239"/><wd nm="230" rd="537,0:602"/><wd nm="230.0000" rd="512,0:456"/><wd nm="23031.298" rd="59,0:427,686"/><wd nm="23032.058" rd="59,0:440,751"/><wd nm="23052.778" rd="59,0:504,585"/><wd nm="23052.815" rd="59,0:517,598"/><wd nm="23157e" rd="425,0:271"/><wd nm="232" rd="249,0:1998"/><wd nm="232062746055483e" rd="505,0:336"/><wd nm="23252052370e" rd="505,0:468"/><wd nm="234" rd="53,0:828,849,870,891,912|369,0:318|467,0:1268|522,0:544|527,0:549|534,0:2400,2425,2503|537,0:436,482,502"/><wd nm="234.67을" rd="426,0:641"/><wd nm="2341" rd="49,0:241,700"/><wd nm="2345" rd="191,0:575|192,0:205|198,0:329|200,0:218|218,0:517|531,0:489"/><wd nm="23456" rd="522,0:518|527,0:523"/><wd nm="234567890" rd="448,0:324,495"/><wd nm="234567890123" rd="531,0:474"/><wd nm="23467를" rd="422,0:281|427,0:261|429,0:255"/><wd nm="23467이" rd="422,0:293|427,0:273|429,0:265"/><wd nm="234e" rd="534,0:2481"/><wd nm="235.0000" rd="512,0:374"/><wd nm="235.1000" rd="512,0:304"/><wd nm="235.1500" rd="512,0:228"/><wd nm="235.1538" rd="512,0:205,281,351,432,515"/><wd nm="235.1538에서" rd="512,0:388,467"/><wd nm="235.1538을" rd="512,0:166,242"/><wd nm="235.1538의" rd="512,0:315"/><wd nm="236335337e" rd="505,0:380"/><wd nm="2368236335337e" rd="505,0:380"/><wd nm="237.5" rd="560,0:899"/><wd nm="2370e" rd="505,0:468"/><wd nm="23757300e" rd="425,0:685"/><wd nm="237573을" rd="425,0:664"/><wd nm="23e" rd="426,0:241|537,0:268"/><wd nm="23xxx" rd="527,0:478|528,0:302"/><wd nm="23로" rd="411,0:79,329|435,0:126,628"/><wd nm="23바이트" rd="431,0:692"/><wd nm="23비트이다" rd="412,0:472"/><wd nm="24" rd="11,0:2897|31,0:495|49,0:1240,1254|120,0:66|241,0:1608|246,0:1584|249,0:1827|270,0:344|317,0:135|323,0:1320|327,0:179|372,0:870|441,0:860|464,0:2112,2147|534,0:882,1301,1455|538,0:647|539,0:756"/><wd nm="24.0" rd="486,0:544"/><wd nm="2400" rd="323,0:235|329,0:840"/><wd nm="241" rd="501,0:421|562,0:662"/><wd nm="24323252052370e" rd="505,0:468"/><wd nm="24342" rd="70,0:154"/><wd nm="24465" rd="70,0:128"/><wd nm="24gb이면" rd="23,0:1317"/><wd nm="24mb" rd="23,0:1297"/><wd nm="24x7" rd="37,0:855"/><wd nm="24개를" rd="558,0:1064"/><wd nm="24개의" rd="464,0:2067"/><wd nm="24시간" rd="27,0:69|419,0:136"/><wd nm="24와" rd="300,0:316"/><wd nm="24이다" rd="541,0:355|542,0:739|544,0:1350|556,0:966"/><wd nm="25" rd="6,0:587,626,1050,1128|49,0:374|59,0:565,850|239,0:199,656|243,0:1954|247,0:1328|249,0:1872|372,0:878|509,0:272|534,0:1375,1400,1549,1664|539,0:589,620,706,799|560,0:873|567,0:721|568,0:1471,1719|569,0:6028"/><wd nm="25,000" rd="323,0:537|329,0:3147"/><wd nm="250" rd="173,0:319|175,0:887,2312,3301,4632,5478"/><wd nm="25000" rd="7,0:2486,2529|323,0:116|329,0:672,3193"/><wd nm="250738585072014e" rd="425,0:246"/><wd nm="252052370e" rd="505,0:468"/><wd nm="2523031.298" rd="59,0:427,686"/><wd nm="2523032.058" rd="59,0:440,751"/><wd nm="2523052.778" rd="59,0:504,585"/><wd nm="2523052.815" rd="59,0:517,598"/><wd nm="255" rd="25,0:153|341,0:2714|372,0:405,498,524|374,0:143|375,0:378|378,0:102|379,0:115|381,0:186|382,0:228,311|383,0:138|384,0:115,172|386,0:99|387,0:111,154|392,0:135|393,0:88,111,267,330,650,707|394,0:151,174,393|395,0:79,111,140,347,375|396,0:78,102,360|397,0:117,147|398,0:87,202|399,0:96,120,153|400,0:93,117,355|401,0:146,170,408|402,0:96,127,164|403,0:83,107,193,258,341|404,0:88,116,150,222|405,0:102|406,0:115|407,0:97,128,162,585,629|408,0:89,745"/><wd nm="255이다" rd="424,0:884"/><wd nm="255자를" rd="586,0:1483"/><wd nm="255자이다" rd="579,0:270"/><wd nm="256" rd="41,0:619|405,0:262|406,0:158|565,0:585,671"/><wd nm="25674323757300e" rd="425,0:685"/><wd nm="256743237573을" rd="425,0:664"/><wd nm="256자이다" rd="451,0:289"/><wd nm="257" rd="236,0:5489|565,0:556,646"/><wd nm="258" rd="565,0:619,953"/><wd nm="25분이므로" rd="6,0:513"/><wd nm="25에" rd="59,0:885"/><wd nm="26" rd="41,0:238,494,1131|53,0:921|249,0:1917|372,0:884|560,0:838|562,0:1103"/><wd nm="260" rd="562,0:669"/><wd nm="263" rd="562,0:1119"/><wd nm="27" rd="7,0:6589|53,0:726,743,900|59,0:341,463,477,540,554,621,635,732,797|372,0:891"/><wd nm="271" rd="562,0:676"/><wd nm="2746055483e" rd="505,0:336"/><wd nm="2766에서부터" rd="260,0:1808"/><wd nm="2767이" rd="579,0:1998"/><wd nm="2767이다" rd="429,0:117|579,0:1991"/><wd nm="2768에서" rd="429,0:110"/><wd nm="27967" rd="612,0:1444"/><wd nm="27분에" rd="59,0:316"/><wd nm="28" rd="53,0:879|405,0:466|406,0:348|485,0:478|554,0:523,525|556,0:822,824|560,0:867"/><wd nm="281" rd="560,0:714,745,776,807"/><wd nm="2823e" rd="426,0:241"/><wd nm="283" rd="560,0:652,683"/><wd nm="2840968047e" rd="505,0:270,314,358,402,446"/><wd nm="28433" rd="61,0:1459,3977"/><wd nm="28433,40820" rd="61,0:627"/><wd nm="28434" rd="61,0:934"/><wd nm="28435" rd="61,0:951"/><wd nm="28436" rd="61,0:968"/><wd nm="28437" rd="61,0:985"/><wd nm="28438" rd="61,0:1002"/><wd nm="28443" rd="61,0:4007"/><wd nm="28443,40821" rd="61,0:1034,2792,3363,4137"/><wd nm="28444" rd="61,0:1336,3094,3665,4622"/><wd nm="28445" rd="61,0:1353,3111,3682,4656"/><wd nm="28446" rd="61,0:1370,3128,3699,4690"/><wd nm="28447" rd="61,0:1387,3145,3716,4724"/><wd nm="28448" rd="61,0:1404,3162,3733,4758"/><wd nm="2858058412e" rd="505,0:424"/><wd nm="287" rd="243,0:426"/><wd nm="29" rd="53,0:858|236,0:2464,2498,2532,2571,2608,2646,2822,2856,2890,2929,2966,3004,4000|247,0:374|249,0:1962|485,0:399,446|613,0:3162"/><wd nm="29191" rd="49,0:428"/><wd nm="296" rd="562,0:1079"/><wd nm="298" rd="59,0:427,686|562,0:683"/><wd nm="2_1" rd="546,0:451,753,909"/><wd nm="2_1과 event2_2를 다시" rd="546,0:833"/><wd nm="2_2" rd="546,0:461,784,917"/><wd nm="2_2를 다시" rd="546,0:833"/><wd nm="2__p__before_2000" rd="404,0:1372|554,0:598"/><wd nm="2__p__before_2000 분할을" rd="554,0:139"/><wd nm="2__p__before_2008" rd="404,0:1455"/><wd nm="2__p__before_max" rd="551,0:787"/><wd nm="2__p__event1" rd="549,0:507|552,0:560"/><wd nm="2__p__event2" rd="552,0:676"/><wd nm="2__p__event3" rd="549,0:701"/><wd nm="2c34a&apos;를" rd="410,0:205,248|411,0:241,290"/><wd nm="2c34a&apos;이" rd="411,0:304"/><wd nm="2e" rd="505,0:424"/><wd nm="2fer" rd="363,0:721"/><wd nm="2kb" rd="431,0:764"/><wd nm="2kg&apos;" rd="569,0:1420,1440"/><wd nm="2nd" rd="608,0:1055,1389"/><wd nm="2 add" rd="555,0:375"/><wd nm="2 dba" rd="236,0:2514,2553,2590,2872,2911,2948"/><wd nm="2 select" rd="648,0:305"/><wd nm="2 values" rd="556,0:666"/><wd nm="2   &apos;planning&apos;   6000000" rd="31,0:1739,1986"/><wd nm="2 클래스에" rd="607,0:1881"/><wd nm="2 테이블의" rd="558,0:409"/><wd nm="2가" rd="36,0:1541|426,0:662|537,0:263|598,0:1999,2037|603,0:1335,1863,2332,2382,2434,2458,2697|604,0:1464,1800,2061|605,0:635,1515,1593,1897,1943,1968,2161,2319,2388,2448|606,0:970,1417,2025,2580,2642,2921|607,0:1646,1878,1958,2152,2479,2785,3438,3509,3534,3712|608,0:496,954,1013,1043,1476,1653,1721,1783|612,0:1162,1188,1364|613,0:3331,3358,3383|647,0:380"/><wd nm="2가 그" rd="615,0:207"/><wd nm="2개로" rd="430,0:356|432,0:578|435,0:454|543,0:218"/><wd nm="2개를" rd="529,0:519|530,0:941"/><wd nm="2개월을" rd="485,0:406"/><wd nm="2개의" rd="241,0:336|579,0:169|618,0:243"/><wd nm="2나" rd="597,0:2256"/></pk>